LICENSE
aiogram_forms/__init__.py
aiogram_forms/const.py
aiogram_forms/core/__init__.py
aiogram_forms/core/entities.py
aiogram_forms/core/manager.py
aiogram_forms/core/states.py
aiogram_forms/dispatcher.py
aiogram_forms/enums.py
aiogram_forms/errors.py
aiogram_forms/filters.py
aiogram_forms/forms/__init__.py
aiogram_forms/forms/base.py
aiogram_forms/forms/fields.py
aiogram_forms/forms/manager.py
aiogram_forms/forms/validators.py
aiogram_forms/middleware.py
aiogram_forms/types.py
aiogram_forms/utils.py
aiogram_forms-1.1.1.dist-info/LICENSE
aiogram_forms-1.1.1.dist-info/METADATA
aiogram_forms-1.1.1.dist-info/WHEEL
aiogram_forms-1.1.1.dist-info/RECORD
