Metadata-Version: 2.1
Name: aiogram-forms
Version: 1.1.1
Summary: Forms for aiogram
Home-page: https://13g10n.com/docs/aiogram-forms
License: MIT
Keywords: aiogram,telegram,forms
Author: Ivan Borisenko
Author-email: i.13g10n@icloud.com
Requires-Python: >=3.8,<4.0
Classifier: Development Status :: 5 - Production/Stable
Classifier: Environment :: Plugins
Classifier: License :: OSI Approved :: MIT License
Classifier: Programming Language :: Python :: 3
Classifier: Programming Language :: Python :: 3.8
Classifier: Programming Language :: Python :: 3.9
Classifier: Programming Language :: Python :: 3.10
Classifier: Programming Language :: Python :: 3.11
Classifier: Programming Language :: Python :: 3.10
Classifier: Programming Language :: Python :: 3.8
Classifier: Programming Language :: Python :: 3.9
Requires-Dist: aiogram (>=3.0.0b5,<4.0.0)
Project-URL: Repository, https://github.com/13g10n/aiogram-forms
